zimbra_permissions_inspector/__init__.py
zimbra_permissions_inspector/_version.py
zimbra_permissions_inspector/zimbra_permissions_inspector.py
zimbra_permissions_inspector-0.1.data/scripts/_version.py
zimbra_permissions_inspector-0.1.dist-info/LICENSE
zimbra_permissions_inspector-0.1.dist-info/METADATA
zimbra_permissions_inspector-0.1.dist-info/WHEEL
zimbra_permissions_inspector-0.1.dist-info/entry_points.txt
zimbra_permissions_inspector-0.1.dist-info/top_level.txt
zimbra_permissions_inspector-0.1.dist-info/RECORD
