Metadata-Version: 2.1
Name: zimbra-permissions-inspector
Version: 0.1
Summary: Query sending permissions on a Zimbra server
Home-page: https://github.com/tuxedoar/zimbra-permissions-inspector
Author: tuxedoar
Author-email: tuxedoar@gmail.com
License: UNKNOWN
Platform: UNKNOWN
Classifier: Programming Language :: Python :: 3 :: Only
Classifier: Programming Language :: Python :: 3.4
Classifier: License :: OSI Approved :: GNU General Public License v3 (GPLv3)
Classifier: Operating System :: OS Independent
Classifier: Intended Audience :: System Administrators
Classifier: Environment :: Console
Classifier: Topic :: System :: Systems Administration :: Authentication/Directory :: LDAP
Requires-Python: >=3.4
Requires-Dist: python-ldap
